{"name":"Renton USPSA - April 8th 2022 - NW05 Specialty Private Match","date":[2022,4,8],"clubName":"asdf","clubCode":"NW01","participants":[{"shooterNumber":1,"nameFirst":"jonathan","nameLast":"tran","uspsaNumber":"NO_USPSA_NUMBER","isDQed":false,"division":"CARRY_OPTICS","divisonFinish":1,"divisionPoints":458.7881,"dqed":false},{"shooterNumber":2,"nameFirst":"clark","nameLast":"cagle","uspsaNumber":"NO_USPSA_NUMBER","isDQed":false,"division":"CARRY_OPTICS","divisonFinish":2,"divisionPoints":394.1455,"dqed":false},{"shooterNumber":3,"nameFirst":"william","nameLast":"palonis","uspsaNumber":"NO_USPSA_NUMBER","isDQed":false,"division":"CARRY_OPTICS","divisonFinish":3,"divisionPoints":214.7713,"dqed":false},{"shooterNumber":4,"nameFirst":"chris","nameLast":"ries","uspsaNumber":"NO_USPSA_NUMBER","isDQed":false,"division":"LIMITED","divisonFinish":1,"divisionPoints":449.0699,"dqed":false},{"shooterNumber":5,"nameFirst":"alex","nameLast":"skaggs","uspsaNumber":"NO_USPSA_NUMBER","isDQed":false,"division":"LIMITED","divisonFinish":2,"divisionPoints":386.1382,"dqed":false},{"shooterNumber":6,"nameFirst":"jason","nameLast":"edlin","uspsaNumber":"NO_USPSA_NUMBER","isDQed":false,"division":"LIMITED","divisonFinish":3,"divisionPoints":333.6914,"dqed":false},{"shooterNumber":7,"nameFirst":"dallas","nameLast":"wood","uspsaNumber":"NO_USPSA_NUMBER","isDQed":false,"division":"LIMITED","divisonFinish":4,"divisionPoints":307.3314,"dqed":false},{"shooterNumber":8,"nameFirst":"chris","nameLast":"kolster","uspsaNumber":"NO_USPSA_NUMBER","isDQed":false,"division":"LIMITED","divisonFinish":5,"divisionPoints":245.6895,"dqed":false},{"shooterNumber":9,"nameFirst":"johnathan","nameLast":"evans","uspsaNumber":"NO_USPSA_NUMBER","isDQed":false,"division":"LIMITED","divisonFinish":6,"divisionPoints":168.9424,"dqed":false},{"shooterNumber":10,"nameFirst":"austin","nameLast":"hurst","uspsaNumber":"NO_USPSA_NUMBER","isDQed":false,"division":"OPEN","divisonFinish":1,"divisionPoints":380.0,"dqed":false},{"shooterNumber":11,"nameFirst":"kevin","nameLast":"castelo","uspsaNumber":"NO_USPSA_NUMBER","isDQed":true,"division":"OPEN","divisonFinish":2,"divisionPoints":0.0,"dqed":true},{"shooterNumber":12,"nameFirst":"marcel","nameLast":"englmaier","uspsaNumber":"4898","isDQed":false,"division":"PRODUCTION","divisonFinish":1,"divisionPoints":470.0,"dqed":false},{"shooterNumber":13,"nameFirst":"chris","nameLast":"motz","uspsaNumber":"NO_USPSA_NUMBER","isDQed":true,"division":"PRODUCTION","divisonFinish":2,"divisionPoints":0.0,"dqed":true}],"stages":[{"number":1,"name":"The Diesel Special","roundCount":26,"points":130,"scoringType":"COMSTOCK","stringCount":1},{"number":2,"name":"The Hozer","roundCount":24,"points":120,"scoringType":"COMSTOCK","stringCount":1},{"number":3,"name":"5 Boxes","roundCount":26,"points":130,"scoringType":"COMSTOCK","stringCount":1},{"number":4,"name":"Cm 69-420 Smoke Classifiers Every Dsy","roundCount":18,"points":90,"scoringType":"COMSTOCK","stringCount":1}],"participantStageResults":[{"stageNumber":1,"shooterNumber":1,"time":15.78,"stageFinish":1,"hitFactor":7.858,"countA":23,"countC":3,"countD":0,"countMiss":0,"countNoShoot":0,"countProcedural":0},{"stageNumber":1,"shooterNumber":2,"time":14.36,"stageFinish":2,"hitFactor":7.1727,"countA":17,"countC":6,"countD":2,"countMiss":1,"countNoShoot":0,"countProcedural":0},{"stageNumber":1,"shooterNumber":3,"time":27.12,"stageFinish":3,"hitFactor":4.7935,"countA":26,"countC":0,"countD":0,"countMiss":0,"countNoShoot":0,"countProcedural":0},{"stageNumber":1,"shooterNumber":4,"time":28.84,"stageFinish":2,"hitFactor":4.1262,"countA":19,"countC":5,"countD":2,"countMiss":0,"countNoShoot":0,"countProcedural":0},{"stageNumber":1,"shooterNumber":5,"time":25.01,"stageFinish":1,"hitFactor":4.918,"countA":19,"countC":7,"countD":0,"countMiss":0,"countNoShoot":0,"countProcedural":0},{"stageNumber":1,"shooterNumber":6,"time":37.9,"stageFinish":4,"hitFactor":3.1926,"countA":19,"countC":6,"countD":1,"countMiss":0,"countNoShoot":0,"countProcedural":0},{"stageNumber":1,"shooterNumber":7,"time":35.84,"stageFinish":3,"hitFactor":3.5435,"countA":23,"countC":3,"countD":0,"countMiss":0,"countNoShoot":0,"countProcedural":0},{"stageNumber":1,"shooterNumber":8,"time":52.01,"stageFinish":6,"hitFactor":2.3842,"countA":20,"countC":6,"countD":0,"countMiss":0,"countNoShoot":0,"countProcedural":0},{"stageNumber":1,"shooterNumber":9,"time":50.17,"stageFinish":5,"hitFactor":2.3919,"countA":16,"countC":10,"countD":0,"countMiss":0,"countNoShoot":0,"countProcedural":0},{"stageNumber":1,"shooterNumber":10,"time":93.37,"stageFinish":1,"hitFactor":1.2852,"countA":18,"countC":7,"countD":1,"countMiss":0,"countNoShoot":0,"countProcedural":0},{"stageNumber":1,"shooterNumber":11,"time":17.97,"stageFinish":2,"hitFactor":0.0,"countA":14,"countC":8,"countD":4,"countMiss":0,"countNoShoot":0,"countProcedural":0},{"stageNumber":1,"shooterNumber":12,"time":17.61,"stageFinish":1,"hitFactor":6.7007,"countA":21,"countC":4,"countD":1,"countMiss":0,"countNoShoot":0,"countProcedural":0},{"stageNumber":1,"shooterNumber":13,"time":55.07,"stageFinish":2,"hitFactor":0.0,"countA":20,"countC":5,"countD":1,"countMiss":0,"countNoShoot":0,"countProcedural":0},{"stageNumber":2,"shooterNumber":1,"time":8.88,"stageFinish":1,"hitFactor":11.4865,"countA":17,"countC":5,"countD":2,"countMiss":0,"countNoShoot":0,"countProcedural":0},{"stageNumber":2,"shooterNumber":2,"time":8.31,"stageFinish":2,"hitFactor":8.9049,"countA":16,"countC":6,"countD":0,"countMiss":2,"countNoShoot":1,"countProcedural":0},{"stageNumber":2,"shooterNumber":3,"time":15.88,"stageFinish":3,"hitFactor":7.4937,"countA":23,"countC":1,"countD":0,"countMiss":0,"countNoShoot":0,"countProcedural":0},{"stageNumber":2,"shooterNumber":4,"time":10.46,"stageFinish":1,"hitFactor":9.4646,"countA":11,"countC":9,"countD":4,"countMiss":0,"countNoShoot":0,"countProcedural":0},{"stageNumber":2,"shooterNumber":5,"time":12.97,"stageFinish":2,"hitFactor":8.5582,"countA":19,"countC":3,"countD":2,"countMiss":0,"countNoShoot":0,"countProcedural":0},{"stageNumber":2,"shooterNumber":6,"time":14.0,"stageFinish":3,"hitFactor":8.3571,"countA":21,"countC":3,"countD":0,"countMiss":0,"countNoShoot":0,"countProcedural":0},{"stageNumber":2,"shooterNumber":7,"time":14.69,"stageFinish":4,"hitFactor":7.2839,"countA":17,"countC":4,"countD":3,"countMiss":0,"countNoShoot":0,"countProcedural":0},{"stageNumber":2,"shooterNumber":8,"time":23.76,"stageFinish":5,"hitFactor":4.8822,"countA":20,"countC":4,"countD":0,"countMiss":0,"countNoShoot":0,"countProcedural":0},{"stageNumber":2,"shooterNumber":9,"time":28.15,"stageFinish":6,"hitFactor":4.1918,"countA":22,"countC":2,"countD":0,"countMiss":0,"countNoShoot":0,"countProcedural":0},{"stageNumber":2,"shooterNumber":10,"time":15.19,"stageFinish":1,"hitFactor":5.3983,"countA":16,"countC":4,"countD":3,"countMiss":1,"countNoShoot":1,"countProcedural":0},{"stageNumber":2,"shooterNumber":11,"time":9.08,"stageFinish":2,"hitFactor":0.0,"countA":18,"countC":5,"countD":1,"countMiss":0,"countNoShoot":0,"countProcedural":0},{"stageNumber":2,"shooterNumber":12,"time":10.83,"stageFinish":1,"hitFactor":9.0489,"countA":14,"countC":9,"countD":1,"countMiss":0,"countNoShoot":0,"countProcedural":0},{"stageNumber":2,"shooterNumber":13,"time":28.18,"stageFinish":2,"hitFactor":0.0,"countA":20,"countC":4,"countD":0,"countMiss":0,"countNoShoot":0,"countProcedural":0},{"stageNumber":3,"shooterNumber":1,"time":26.19,"stageFinish":2,"hitFactor":4.8874,"countA":25,"countC":1,"countD":0,"countMiss":0,"countNoShoot":0,"countProcedural":0},{"stageNumber":3,"shooterNumber":2,"time":23.37,"stageFinish":1,"hitFactor":5.3487,"countA":21,"countC":5,"countD":0,"countMiss":0,"countNoShoot":0,"countProcedural":0},{"stageNumber":3,"shooterNumber":3,"time":54.83,"stageFinish":3,"hitFactor":2.3527,"countA":25,"countC":1,"countD":0,"countMiss":0,"countNoShoot":0,"countProcedural":0},{"stageNumber":3,"shooterNumber":4,"time":34.57,"stageFinish":1,"hitFactor":3.4134,"countA":16,"countC":9,"countD":1,"countMiss":0,"countNoShoot":0,"countProcedural":0},{"stageNumber":3,"shooterNumber":5,"time":34.04,"stageFinish":2,"hitFactor":2.4089,"countA":18,"countC":5,"countD":1,"countMiss":2,"countNoShoot":0,"countProcedural":1},{"stageNumber":3,"shooterNumber":6,"time":58.16,"stageFinish":3,"hitFactor":2.1149,"countA":21,"countC":4,"countD":1,"countMiss":0,"countNoShoot":0,"countProcedural":0},{"stageNumber":3,"shooterNumber":7,"time":46.5,"stageFinish":5,"hitFactor":1.871,"countA":11,"countC":13,"countD":0,"countMiss":2,"countNoShoot":0,"countProcedural":0},{"stageNumber":3,"shooterNumber":8,"time":54.03,"stageFinish":4,"hitFactor":1.9989,"countA":14,"countC":7,"countD":5,"countMiss":0,"countNoShoot":0,"countProcedural":0},{"stageNumber":3,"shooterNumber":9,"time":76.07,"stageFinish":6,"hitFactor":1.3803,"countA":19,"countC":4,"countD":2,"countMiss":1,"countNoShoot":0,"countProcedural":0},{"stageNumber":3,"shooterNumber":10,"time":49.29,"stageFinish":1,"hitFactor":2.0897,"countA":17,"countC":6,"countD":2,"countMiss":1,"countNoShoot":0,"countProcedural":0},{"stageNumber":3,"shooterNumber":11,"time":27.8,"stageFinish":2,"hitFactor":0.0,"countA":21,"countC":5,"countD":0,"countMiss":0,"countNoShoot":0,"countProcedural":1},{"stageNumber":3,"shooterNumber":12,"time":33.65,"stageFinish":1,"hitFactor":3.2689,"countA":17,"countC":8,"countD":1,"countMiss":0,"countNoShoot":0,"countProcedural":0},{"stageNumber":3,"shooterNumber":13,"time":48.97,"stageFinish":2,"hitFactor":0.0,"countA":10,"countC":4,"countD":2,"countMiss":6,"countNoShoot":0,"countProcedural":0},{"stageNumber":4,"shooterNumber":1,"time":15.63,"stageFinish":1,"hitFactor":5.2463,"countA":14,"countC":4,"countD":0,"countMiss":0,"countNoShoot":0,"countProcedural":0},{"stageNumber":4,"shooterNumber":2,"time":16.68,"stageFinish":2,"hitFactor":3.0576,"countA":11,"countC":3,"countD":2,"countMiss":2,"countNoShoot":0,"countProcedural":0},{"stageNumber":4,"shooterNumber":3,"time":0.0,"stageFinish":3,"hitFactor":0.0,"countA":2,"countC":0,"countD":0,"countMiss":0,"countNoShoot":0,"countProcedural":0},{"stageNumber":4,"shooterNumber":4,"time":17.3,"stageFinish":1,"hitFactor":4.8555,"countA":14,"countC":3,"countD":1,"countMiss":0,"countNoShoot":0,"countProcedural":0},{"stageNumber":4,"shooterNumber":5,"time":21.89,"stageFinish":3,"hitFactor":3.0151,"countA":10,"countC":6,"countD":1,"countMiss":1,"countNoShoot":0,"countProcedural":0},{"stageNumber":4,"shooterNumber":6,"time":24.5,"stageFinish":2,"hitFactor":3.3878,"countA":13,"countC":4,"countD":1,"countMiss":0,"countNoShoot":0,"countProcedural":0},{"stageNumber":4,"shooterNumber":7,"time":24.81,"stageFinish":4,"hitFactor":2.7005,"countA":7,"countC":10,"countD":1,"countMiss":0,"countNoShoot":1,"countProcedural":0},{"stageNumber":4,"shooterNumber":8,"time":32.39,"stageFinish":5,"hitFactor":2.4082,"countA":10,"countC":6,"countD":2,"countMiss":0,"countNoShoot":0,"countProcedural":0},{"stageNumber":4,"shooterNumber":9,"time":0.0,"stageFinish":6,"hitFactor":0.0,"countA":2,"countC":0,"countD":0,"countMiss":0,"countNoShoot":0,"countProcedural":0},{"stageNumber":4,"shooterNumber":10,"time":14.22,"stageFinish":1,"hitFactor":0.0,"countA":12,"countC":4,"countD":2,"countMiss":0,"countNoShoot":0,"countProcedural":14},{"stageNumber":4,"shooterNumber":11,"time":0.0,"stageFinish":2,"hitFactor":0.0,"countA":2,"countC":0,"countD":0,"countMiss":0,"countNoShoot":0,"countProcedural":0},{"stageNumber":4,"shooterNumber":12,"time":14.45,"stageFinish":1,"hitFactor":3.8062,"countA":8,"countC":8,"countD":1,"countMiss":1,"countNoShoot":0,"countProcedural":0}]}