{"name":"Custer USPSA Jun 6, 2021","date":[2021,6,6],"clubName":"Custer Sportsmens Club","clubCode":"NW07","participants":[{"shooterNumber":1,"nameFirst":"sorida","nameLast":"eap","uspsaNumber":"l","isDQed":false,"division":"CARRY_OPTICS","divisonFinish":1,"dqed":false},{"shooterNumber":2,"nameFirst":"colin","nameLast":"corden","uspsaNumber":"a","isDQed":false,"division":"CARRY_OPTICS","divisonFinish":2,"dqed":false},{"shooterNumber":3,"nameFirst":"rob","nameLast":"loo","uspsaNumber":"l","isDQed":false,"division":"CARRY_OPTICS","divisonFinish":3,"dqed":false},{"shooterNumber":4,"nameFirst":"gregg","nameLast":"straathof","uspsaNumber":"a","isDQed":false,"division":"CARRY_OPTICS","divisonFinish":4,"dqed":false},{"shooterNumber":5,"nameFirst":"steve","nameLast":"taylor","uspsaNumber":"a","isDQed":false,"division":"CARRY_OPTICS","divisonFinish":5,"dqed":false},{"shooterNumber":6,"nameFirst":"jason","nameLast":"james","uspsaNumber":"ty","isDQed":false,"division":"CARRY_OPTICS","divisonFinish":6,"dqed":false},{"shooterNumber":7,"nameFirst":"dean","nameLast":"clark","uspsaNumber":"a","isDQed":false,"division":"CARRY_OPTICS","divisonFinish":7,"dqed":false},{"shooterNumber":8,"nameFirst":"anna","nameLast":"skurdal","uspsaNumber":"a","isDQed":false,"division":"CARRY_OPTICS","divisonFinish":8,"dqed":false},{"shooterNumber":9,"nameFirst":"squire","nameLast":"tomasie","uspsaNumber":"l","isDQed":false,"division":"CARRY_OPTICS","divisonFinish":9,"dqed":false},{"shooterNumber":10,"nameFirst":"kay","nameLast":"patterson","uspsaNumber":"ty","isDQed":false,"division":"CARRY_OPTICS","divisonFinish":10,"dqed":false},{"shooterNumber":11,"nameFirst":"jody","nameLast":"hernandez","uspsaNumber":"notamember","isDQed":false,"division":"CARRY_OPTICS","divisonFinish":11,"dqed":false},{"shooterNumber":12,"nameFirst":"ken","nameLast":"pavlick","uspsaNumber":"ty","isDQed":false,"division":"CARRY_OPTICS","divisonFinish":12,"dqed":false},{"shooterNumber":13,"nameFirst":"vinh","nameLast":"hoang","uspsaNumber":"l","isDQed":false,"division":"LIMITED","divisonFinish":1,"dqed":false},{"shooterNumber":14,"nameFirst":"stuart","nameLast":"wilson","uspsaNumber":"ty","isDQed":false,"division":"LIMITED","divisonFinish":2,"dqed":false},{"shooterNumber":15,"nameFirst":"phillip","nameLast":"oconnor","uspsaNumber":"a","isDQed":false,"division":"LIMITED","divisonFinish":3,"dqed":false},{"shooterNumber":16,"nameFirst":"chris","nameLast":"tedford","uspsaNumber":"ty","isDQed":false,"division":"LIMITED","divisonFinish":4,"dqed":false},{"shooterNumber":17,"nameFirst":"kevin","nameLast":"roberts","uspsaNumber":"l","isDQed":false,"division":"LIMITED","divisonFinish":5,"dqed":false},{"shooterNumber":18,"nameFirst":"mark","nameLast":"vogel","uspsaNumber":"ty","isDQed":false,"division":"LIMITED","divisonFinish":6,"dqed":false},{"shooterNumber":19,"nameFirst":"duane","nameLast":"duxbury","uspsaNumber":"a","isDQed":false,"division":"LIMITED","divisonFinish":7,"dqed":false},{"shooterNumber":20,"nameFirst":"clifford","nameLast":"aguilar","uspsaNumber":"l","isDQed":false,"division":"LIMITED","divisonFinish":8,"dqed":false},{"shooterNumber":21,"nameFirst":"scott","nameLast":"mcintosh","uspsaNumber":"a","isDQed":false,"division":"LIMITED","divisonFinish":9,"dqed":false},{"shooterNumber":22,"nameFirst":"andi","nameLast":"dyer","uspsaNumber":"a","isDQed":false,"division":"LIMITED","divisonFinish":10,"dqed":false},{"shooterNumber":23,"nameFirst":"peter","nameLast":"ryakhovskiy","uspsaNumber":"ty","isDQed":false,"division":"OPEN","divisonFinish":1,"dqed":false},{"shooterNumber":24,"nameFirst":"ryan","nameLast":"halwick","uspsaNumber":"a","isDQed":false,"division":"OPEN","divisonFinish":2,"dqed":false},{"shooterNumber":25,"nameFirst":"floyd","nameLast":"shoemaker","uspsaNumber":"l","isDQed":false,"division":"OPEN","divisonFinish":3,"dqed":false},{"shooterNumber":26,"nameFirst":"rae arsen","nameLast":"baleros","uspsaNumber":"a","isDQed":false,"division":"OPEN","divisonFinish":4,"dqed":false},{"shooterNumber":27,"nameFirst":"damon","nameLast":"donner","uspsaNumber":"a","isDQed":false,"division":"OPEN","divisonFinish":5,"dqed":false},{"shooterNumber":28,"nameFirst":"gary","nameLast":"roessel","uspsaNumber":"a","isDQed":false,"division":"OPEN","divisonFinish":6,"dqed":false},{"shooterNumber":29,"nameFirst":"melissa","nameLast":"wilson","uspsaNumber":"fy","isDQed":false,"division":"OPEN","divisonFinish":7,"dqed":false},{"shooterNumber":30,"nameFirst":"dustin","nameLast":"hansen","uspsaNumber":"notamember","isDQed":false,"division":"OPEN","divisonFinish":8,"dqed":false},{"shooterNumber":31,"nameFirst":"randall","nameLast":"hess","uspsaNumber":"ty","isDQed":false,"division":"OPEN","divisonFinish":9,"dqed":false},{"shooterNumber":32,"nameFirst":"greg","nameLast":"purcell","uspsaNumber":"fy","isDQed":false,"division":"PCC","divisonFinish":1,"dqed":false},{"shooterNumber":33,"nameFirst":"mike","nameLast":"leander","uspsaNumber":"a","isDQed":false,"division":"PCC","divisonFinish":2,"dqed":false},{"shooterNumber":34,"nameFirst":"james","nameLast":"dong","uspsaNumber":"fy","isDQed":false,"division":"PCC","divisonFinish":3,"dqed":false},{"shooterNumber":35,"nameFirst":"steven","nameLast":"roessel","uspsaNumber":"a","isDQed":false,"division":"PCC","divisonFinish":4,"dqed":false},{"shooterNumber":36,"nameFirst":"james","nameLast":"fenlin","uspsaNumber":"ty","isDQed":false,"division":"PCC","divisonFinish":5,"dqed":false},{"shooterNumber":37,"nameFirst":"don","nameLast":"carroll","uspsaNumber":"a","isDQed":false,"division":"PRODUCTION","divisonFinish":1,"dqed":false},{"shooterNumber":38,"nameFirst":"carlo","nameLast":"sulicipan","uspsaNumber":"ty","isDQed":false,"division":"PRODUCTION","divisonFinish":2,"dqed":false},{"shooterNumber":39,"nameFirst":"eric","nameLast":"hausner","uspsaNumber":"a","isDQed":false,"division":"PRODUCTION","divisonFinish":3,"dqed":false},{"shooterNumber":40,"nameFirst":"gregory","nameLast":"vanlandingham","uspsaNumber":"a","isDQed":false,"division":"SINGLE_STACK","divisonFinish":1,"dqed":false},{"shooterNumber":41,"nameFirst":"jaxon","nameLast":"scofield","uspsaNumber":"a","isDQed":false,"division":"SINGLE_STACK","divisonFinish":2,"dqed":false},{"shooterNumber":42,"nameFirst":"lynn","nameLast":"wise","uspsaNumber":"a","isDQed":false,"division":"SINGLE_STACK","divisonFinish":3,"dqed":false}],"stages":[{"number":1,"name":"Bay 2 Stage 1","roundCount":20,"points":100,"scoringType":"COMSTOCK","stringCount":1},{"number":2,"name":"Bay 3 Golden Bullet Standards","roundCount":24,"points":120,"scoringType":"VIRGINIA","stringCount":2},{"number":3,"name":"Bay 4 Stage 3","roundCount":28,"points":140,"scoringType":"COMSTOCK","stringCount":1},{"number":4,"name":"Bay 5 Stage 4","roundCount":12,"points":60,"scoringType":"COMSTOCK","stringCount":1},{"number":5,"name":"Bay 6 Stage 5","roundCount":22,"points":110,"scoringType":"COMSTOCK","stringCount":1},{"number":6,"name":"Bay 8 Stage 6","roundCount":30,"points":150,"scoringType":"COMSTOCK","stringCount":1}],"participantStageResults":[{"stageNumber":1,"shooterNumber":1,"time":12.38,"stageFinish":3,"hitFactor":7.5929,"countA":17,"countC":3,"countD":0,"countMiss":0,"countNoShoot":0,"countProcedural":0},{"stageNumber":1,"shooterNumber":2,"time":9.98,"stageFinish":1,"hitFactor":10.02,"countA":20,"countC":0,"countD":0,"countMiss":0,"countNoShoot":0,"countProcedural":0},{"stageNumber":1,"shooterNumber":3,"time":14.74,"stageFinish":9,"hitFactor":5.156,"countA":13,"countC":7,"countD":0,"countMiss":0,"countNoShoot":1,"countProcedural":0},{"stageNumber":1,"shooterNumber":4,"time":13.84,"stageFinish":4,"hitFactor":7.2254,"countA":20,"countC":0,"countD":0,"countMiss":0,"countNoShoot":0,"countProcedural":0},{"stageNumber":1,"shooterNumber":5,"time":14.01,"stageFinish":7,"hitFactor":6.0671,"countA":19,"countC":0,"countD":0,"countMiss":1,"countNoShoot":0,"countProcedural":0},{"stageNumber":1,"shooterNumber":6,"time":12.58,"stageFinish":2,"hitFactor":7.6312,"countA":18,"countC":2,"countD":0,"countMiss":0,"countNoShoot":0,"countProcedural":0},{"stageNumber":1,"shooterNumber":7,"time":13.69,"stageFinish":5,"hitFactor":7.0124,"countA":18,"countC":2,"countD":0,"countMiss":0,"countNoShoot":0,"countProcedural":0},{"stageNumber":1,"shooterNumber":8,"time":17.4,"stageFinish":8,"hitFactor":5.7471,"countA":20,"countC":0,"countD":0,"countMiss":0,"countNoShoot":0,"countProcedural":0},{"stageNumber":1,"shooterNumber":9,"time":16.43,"stageFinish":6,"hitFactor":6.0864,"countA":20,"countC":0,"countD":0,"countMiss":0,"countNoShoot":0,"countProcedural":0},{"stageNumber":1,"shooterNumber":10,"time":24.49,"stageFinish":11,"hitFactor":4.0016,"countA":19,"countC":1,"countD":0,"countMiss":0,"countNoShoot":0,"countProcedural":0},{"stageNumber":1,"shooterNumber":11,"time":28.57,"stageFinish":12,"hitFactor":3.3602,"countA":18,"countC":2,"countD":0,"countMiss":0,"countNoShoot":0,"countProcedural":0},{"stageNumber":1,"shooterNumber":12,"time":19.73,"stageFinish":10,"hitFactor":4.3588,"countA":13,"countC":7,"countD":0,"countMiss":0,"countNoShoot":0,"countProcedural":0},{"stageNumber":1,"shooterNumber":13,"time":12.49,"stageFinish":1,"hitFactor":8.0064,"countA":20,"countC":0,"countD":0,"countMiss":0,"countNoShoot":0,"countProcedural":0},{"stageNumber":1,"shooterNumber":14,"time":15.01,"stageFinish":2,"hitFactor":6.3291,"countA":15,"countC":5,"countD":0,"countMiss":0,"countNoShoot":0,"countProcedural":0},{"stageNumber":1,"shooterNumber":15,"time":14.0,"stageFinish":4,"hitFactor":5.6429,"countA":17,"countC":0,"countD":2,"countMiss":1,"countNoShoot":0,"countProcedural":0},{"stageNumber":1,"shooterNumber":16,"time":16.28,"stageFinish":3,"hitFactor":6.0811,"countA":19,"countC":1,"countD":0,"countMiss":0,"countNoShoot":0,"countProcedural":0},{"stageNumber":1,"shooterNumber":17,"time":18.27,"stageFinish":6,"hitFactor":5.4735,"countA":20,"countC":0,"countD":0,"countMiss":0,"countNoShoot":0,"countProcedural":0},{"stageNumber":1,"shooterNumber":18,"time":18.86,"stageFinish":7,"hitFactor":4.772,"countA":20,"countC":0,"countD":0,"countMiss":0,"countNoShoot":1,"countProcedural":0},{"stageNumber":1,"shooterNumber":19,"time":28.22,"stageFinish":8,"hitFactor":3.2601,"countA":16,"countC":4,"countD":0,"countMiss":0,"countNoShoot":0,"countProcedural":0},{"stageNumber":1,"shooterNumber":20,"time":17.06,"stageFinish":5,"hitFactor":5.6272,"countA":18,"countC":2,"countD":0,"countMiss":0,"countNoShoot":0,"countProcedural":0},{"stageNumber":1,"shooterNumber":21,"time":34.38,"stageFinish":9,"hitFactor":2.5887,"countA":19,"countC":1,"countD":0,"countMiss":0,"countNoShoot":1,"countProcedural":0},{"stageNumber":1,"shooterNumber":22,"time":28.61,"stageFinish":10,"hitFactor":1.6078,"countA":16,"countC":2,"countD":0,"countMiss":2,"countNoShoot":0,"countProcedural":2},{"stageNumber":1,"shooterNumber":23,"time":10.63,"stageFinish":1,"hitFactor":9.4073,"countA":20,"countC":0,"countD":0,"countMiss":0,"countNoShoot":0,"countProcedural":0},{"stageNumber":1,"shooterNumber":24,"time":10.55,"stageFinish":2,"hitFactor":8.8152,"countA":15,"countC":4,"countD":1,"countMiss":0,"countNoShoot":0,"countProcedural":0},{"stageNumber":1,"shooterNumber":25,"time":13.62,"stageFinish":4,"hitFactor":7.0485,"countA":16,"countC":4,"countD":0,"countMiss":0,"countNoShoot":0,"countProcedural":0},{"stageNumber":1,"shooterNumber":26,"time":13.19,"stageFinish":3,"hitFactor":7.5057,"countA":19,"countC":1,"countD":0,"countMiss":0,"countNoShoot":0,"countProcedural":0},{"stageNumber":1,"shooterNumber":27,"time":15.96,"stageFinish":5,"hitFactor":6.203,"countA":19,"countC":1,"countD":0,"countMiss":0,"countNoShoot":0,"countProcedural":0},{"stageNumber":1,"shooterNumber":28,"time":17.03,"stageFinish":7,"hitFactor":5.5197,"countA":17,"countC":3,"countD":0,"countMiss":0,"countNoShoot":0,"countProcedural":0},{"stageNumber":1,"shooterNumber":29,"time":16.79,"stageFinish":6,"hitFactor":5.5986,"countA":16,"countC":3,"countD":1,"countMiss":0,"countNoShoot":0,"countProcedural":0},{"stageNumber":1,"shooterNumber":30,"time":26.62,"stageFinish":9,"hitFactor":3.6814,"countA":19,"countC":1,"countD":0,"countMiss":0,"countNoShoot":0,"countProcedural":0},{"stageNumber":1,"shooterNumber":31,"time":24.29,"stageFinish":8,"hitFactor":4.1169,"countA":20,"countC":0,"countD":0,"countMiss":0,"countNoShoot":0,"countProcedural":0},{"stageNumber":1,"shooterNumber":32,"time":11.46,"stageFinish":1,"hitFactor":8.726,"countA":20,"countC":0,"countD":0,"countMiss":0,"countNoShoot":0,"countProcedural":0},{"stageNumber":1,"shooterNumber":33,"time":13.76,"stageFinish":3,"hitFactor":7.1221,"countA":19,"countC":1,"countD":0,"countMiss":0,"countNoShoot":0,"countProcedural":0},{"stageNumber":1,"shooterNumber":34,"time":12.5,"stageFinish":2,"hitFactor":7.84,"countA":19,"countC":1,"countD":0,"countMiss":0,"countNoShoot":0,"countProcedural":0},{"stageNumber":1,"shooterNumber":35,"time":14.6,"stageFinish":4,"hitFactor":6.5753,"countA":18,"countC":2,"countD":0,"countMiss":0,"countNoShoot":0,"countProcedural":0},{"stageNumber":1,"shooterNumber":36,"time":16.19,"stageFinish":5,"hitFactor":6.1767,"countA":20,"countC":0,"countD":0,"countMiss":0,"countNoShoot":0,"countProcedural":0},{"stageNumber":1,"shooterNumber":37,"time":11.81,"stageFinish":1,"hitFactor":8.4674,"countA":20,"countC":0,"countD":0,"countMiss":0,"countNoShoot":0,"countProcedural":0},{"stageNumber":1,"shooterNumber":38,"time":15.14,"stageFinish":2,"hitFactor":6.605,"countA":20,"countC":0,"countD":0,"countMiss":0,"countNoShoot":0,"countProcedural":0},{"stageNumber":1,"shooterNumber":39,"time":25.81,"stageFinish":3,"hitFactor":3.8745,"countA":20,"countC":0,"countD":0,"countMiss":0,"countNoShoot":0,"countProcedural":0},{"stageNumber":1,"shooterNumber":40,"time":13.16,"stageFinish":1,"hitFactor":7.5228,"countA":19,"countC":1,"countD":0,"countMiss":0,"countNoShoot":0,"countProcedural":0},{"stageNumber":1,"shooterNumber":41,"time":20.43,"stageFinish":2,"hitFactor":4.3074,"countA":18,"countC":2,"countD":0,"countMiss":0,"countNoShoot":1,"countProcedural":0},{"stageNumber":1,"shooterNumber":42,"time":29.18,"stageFinish":3,"hitFactor":2.8101,"countA":14,"countC":3,"countD":3,"countMiss":0,"countNoShoot":0,"countProcedural":0},{"stageNumber":2,"shooterNumber":1,"time":18.02,"stageFinish":4,"hitFactor":4.606,"countA":14,"countC":7,"countD":2,"countMiss":1,"countNoShoot":0,"countProcedural":0},{"stageNumber":2,"shooterNumber":2,"time":18.97,"stageFinish":5,"hitFactor":4.5862,"countA":15,"countC":7,"countD":1,"countMiss":1,"countNoShoot":0,"countProcedural":0},{"stageNumber":2,"shooterNumber":3,"time":21.22,"stageFinish":3,"hitFactor":4.7125,"countA":15,"countC":8,"countD":1,"countMiss":0,"countNoShoot":0,"countProcedural":0},{"stageNumber":2,"shooterNumber":4,"time":19.7,"stageFinish":2,"hitFactor":4.8223,"countA":18,"countC":5,"countD":0,"countMiss":1,"countNoShoot":0,"countProcedural":0},{"stageNumber":2,"shooterNumber":5,"time":20.62,"stageFinish":1,"hitFactor":5.3346,"countA":19,"countC":5,"countD":0,"countMiss":0,"countNoShoot":0,"countProcedural":0},{"stageNumber":2,"shooterNumber":6,"time":20.71,"stageFinish":6,"hitFactor":4.2974,"countA":17,"countC":4,"countD":2,"countMiss":1,"countNoShoot":0,"countProcedural":0},{"stageNumber":2,"shooterNumber":7,"time":31.27,"stageFinish":9,"hitFactor":2.3665,"countA":17,"countC":2,"countD":3,"countMiss":2,"countNoShoot":0,"countProcedural":0},{"stageNumber":2,"shooterNumber":8,"time":29.4,"stageFinish":8,"hitFactor":3.1633,"countA":17,"countC":6,"countD":0,"countMiss":1,"countNoShoot":0,"countProcedural":0},{"stageNumber":2,"shooterNumber":9,"time":23.46,"stageFinish":7,"hitFactor":3.5379,"countA":13,"countC":9,"countD":1,"countMiss":1,"countNoShoot":0,"countProcedural":0},{"stageNumber":2,"shooterNumber":10,"time":41.73,"stageFinish":12,"hitFactor":1.0544,"countA":17,"countC":6,"countD":1,"countMiss":0,"countNoShoot":0,"countProcedural":6},{"stageNumber":2,"shooterNumber":11,"time":47.43,"stageFinish":11,"hitFactor":1.9186,"countA":22,"countC":0,"countD":1,"countMiss":1,"countNoShoot":0,"countProcedural":1},{"stageNumber":2,"shooterNumber":12,"time":26.48,"stageFinish":10,"hitFactor":2.1526,"countA":9,"countC":4,"countD":10,"countMiss":1,"countNoShoot":0,"countProcedural":0},{"stageNumber":2,"shooterNumber":13,"time":15.32,"stageFinish":1,"hitFactor":6.0052,"countA":16,"countC":4,"countD":3,"countMiss":1,"countNoShoot":0,"countProcedural":0},{"stageNumber":2,"shooterNumber":14,"time":21.19,"stageFinish":3,"hitFactor":4.6248,"countA":10,"countC":10,"countD":4,"countMiss":0,"countNoShoot":0,"countProcedural":0},{"stageNumber":2,"shooterNumber":15,"time":18.73,"stageFinish":5,"hitFactor":3.7373,"countA":10,"countC":8,"countD":4,"countMiss":2,"countNoShoot":0,"countProcedural":0},{"stageNumber":2,"shooterNumber":16,"time":20.46,"stageFinish":4,"hitFactor":3.9101,"countA":14,"countC":7,"countD":1,"countMiss":2,"countNoShoot":0,"countProcedural":0},{"stageNumber":2,"shooterNumber":17,"time":24.32,"stageFinish":2,"hitFactor":4.7286,"countA":19,"countC":5,"countD":0,"countMiss":0,"countNoShoot":0,"countProcedural":0},{"stageNumber":2,"shooterNumber":18,"time":26.85,"stageFinish":7,"hitFactor":2.8678,"countA":13,"countC":6,"countD":4,"countMiss":1,"countNoShoot":0,"countProcedural":0},{"stageNumber":2,"shooterNumber":19,"time":32.3,"stageFinish":9,"hitFactor":2.4458,"countA":12,"countC":9,"countD":2,"countMiss":1,"countNoShoot":0,"countProcedural":0},{"stageNumber":2,"shooterNumber":20,"time":25.01,"stageFinish":6,"hitFactor":3.4386,"countA":10,"countC":11,"countD":3,"countMiss":0,"countNoShoot":0,"countProcedural":0},{"stageNumber":2,"shooterNumber":21,"time":34.65,"stageFinish":8,"hitFactor":2.5108,"countA":11,"countC":9,"countD":3,"countMiss":1,"countNoShoot":0,"countProcedural":0},{"stageNumber":2,"shooterNumber":22,"time":33.44,"stageFinish":10,"hitFactor":2.183,"countA":11,"countC":8,"countD":4,"countMiss":1,"countNoShoot":0,"countProcedural":0},{"stageNumber":2,"shooterNumber":23,"time":18.51,"stageFinish":1,"hitFactor":6.1588,"countA":18,"countC":6,"countD":0,"countMiss":0,"countNoShoot":0,"countProcedural":0},{"stageNumber":2,"shooterNumber":24,"time":17.48,"stageFinish":2,"hitFactor":4.9771,"countA":11,"countC":9,"countD":3,"countMiss":1,"countNoShoot":0,"countProcedural":0},{"stageNumber":2,"shooterNumber":25,"time":19.36,"stageFinish":3,"hitFactor":4.7521,"countA":14,"countC":7,"countD":2,"countMiss":1,"countNoShoot":0,"countProcedural":0},{"stageNumber":2,"shooterNumber":26,"time":18.75,"stageFinish":4,"hitFactor":4.2667,"countA":10,"countC":7,"countD":6,"countMiss":1,"countNoShoot":0,"countProcedural":0},{"stageNumber":2,"shooterNumber":27,"time":24.52,"stageFinish":6,"hitFactor":3.4258,"countA":16,"countC":6,"countD":0,"countMiss":2,"countNoShoot":0,"countProcedural":0},{"stageNumber":2,"shooterNumber":28,"time":36.17,"stageFinish":7,"hitFactor":3.3177,"countA":24,"countC":0,"countD":0,"countMiss":0,"countNoShoot":0,"countProcedural":0},{"stageNumber":2,"shooterNumber":29,"time":34.33,"stageFinish":9,"hitFactor":2.709,"countA":15,"countC":6,"countD":2,"countMiss":1,"countNoShoot":0,"countProcedural":0},{"stageNumber":2,"shooterNumber":30,"time":37.41,"stageFinish":8,"hitFactor":2.8335,"countA":17,"countC":7,"countD":0,"countMiss":0,"countNoShoot":0,"countProcedural":0},{"stageNumber":2,"shooterNumber":31,"time":28.71,"stageFinish":5,"hitFactor":3.6921,"countA":18,"countC":5,"countD":1,"countMiss":0,"countNoShoot":0,"countProcedural":0},{"stageNumber":2,"shooterNumber":32,"time":13.34,"stageFinish":1,"hitFactor":7.6462,"countA":17,"countC":5,"countD":2,"countMiss":0,"countNoShoot":0,"countProcedural":0},{"stageNumber":2,"shooterNumber":33,"time":13.75,"stageFinish":2,"hitFactor":7.1273,"countA":15,"countC":7,"countD":2,"countMiss":0,"countNoShoot":0,"countProcedural":0},{"stageNumber":2,"shooterNumber":34,"time":17.11,"stageFinish":3,"hitFactor":6.5459,"countA":20,"countC":4,"countD":0,"countMiss":0,"countNoShoot":0,"countProcedural":0},{"stageNumber":2,"shooterNumber":35,"time":19.19,"stageFinish":4,"hitFactor":5.8364,"countA":20,"countC":4,"countD":0,"countMiss":0,"countNoShoot":0,"countProcedural":0},{"stageNumber":2,"shooterNumber":36,"time":10.69,"stageFinish":5,"hitFactor":0.0,"countA":6,"countC":5,"countD":0,"countMiss":13,"countNoShoot":0,"countProcedural":0},{"stageNumber":2,"shooterNumber":37,"time":16.72,"stageFinish":1,"hitFactor":6.1005,"countA":16,"countC":7,"countD":1,"countMiss":0,"countNoShoot":0,"countProcedural":0},{"stageNumber":2,"shooterNumber":38,"time":24.5,"stageFinish":2,"hitFactor":4.0816,"countA":16,"countC":6,"countD":2,"countMiss":0,"countNoShoot":0,"countProcedural":0},{"stageNumber":2,"shooterNumber":39,"time":42.39,"stageFinish":3,"hitFactor":2.1703,"countA":21,"countC":2,"countD":1,"countMiss":0,"countNoShoot":0,"countProcedural":2},{"stageNumber":2,"shooterNumber":40,"time":18.44,"stageFinish":1,"hitFactor":5.9111,"countA":15,"countC":8,"countD":1,"countMiss":0,"countNoShoot":0,"countProcedural":0},{"stageNumber":2,"shooterNumber":41,"time":27.69,"stageFinish":2,"hitFactor":2.9975,"countA":15,"countC":6,"countD":2,"countMiss":1,"countNoShoot":0,"countProcedural":1},{"stageNumber":2,"shooterNumber":42,"time":38.33,"stageFinish":3,"hitFactor":1.6958,"countA":9,"countC":8,"countD":6,"countMiss":1,"countNoShoot":0,"countProcedural":0},{"stageNumber":3,"shooterNumber":1,"time":13.42,"stageFinish":1,"hitFactor":9.538,"countA":22,"countC":6,"countD":0,"countMiss":0,"countNoShoot":0,"countProcedural":0},{"stageNumber":3,"shooterNumber":2,"time":14.01,"stageFinish":2,"hitFactor":9.2791,"countA":24,"countC":3,"countD":1,"countMiss":0,"countNoShoot":0,"countProcedural":0},{"stageNumber":3,"shooterNumber":3,"time":14.75,"stageFinish":4,"hitFactor":8.4068,"countA":21,"countC":6,"countD":1,"countMiss":0,"countNoShoot":0,"countProcedural":0},{"stageNumber":3,"shooterNumber":4,"time":16.22,"stageFinish":3,"hitFactor":8.508,"countA":27,"countC":1,"countD":0,"countMiss":0,"countNoShoot":0,"countProcedural":0},{"stageNumber":3,"shooterNumber":5,"time":16.1,"stageFinish":5,"hitFactor":7.7019,"countA":20,"countC":8,"countD":0,"countMiss":0,"countNoShoot":0,"countProcedural":0},{"stageNumber":3,"shooterNumber":6,"time":19.44,"stageFinish":7,"hitFactor":7.0988,"countA":27,"countC":1,"countD":0,"countMiss":0,"countNoShoot":0,"countProcedural":0},{"stageNumber":3,"shooterNumber":7,"time":17.22,"stageFinish":6,"hitFactor":7.6655,"countA":24,"countC":4,"countD":0,"countMiss":0,"countNoShoot":0,"countProcedural":0},{"stageNumber":3,"shooterNumber":8,"time":22.38,"stageFinish":8,"hitFactor":6.2556,"countA":28,"countC":0,"countD":0,"countMiss":0,"countNoShoot":0,"countProcedural":0},{"stageNumber":3,"shooterNumber":9,"time":20.86,"stageFinish":9,"hitFactor":5.6568,"countA":23,"countC":4,"countD":1,"countMiss":0,"countNoShoot":1,"countProcedural":0},{"stageNumber":3,"shooterNumber":10,"time":27.48,"stageFinish":11,"hitFactor":4.5852,"countA":22,"countC":5,"countD":1,"countMiss":0,"countNoShoot":0,"countProcedural":0},{"stageNumber":3,"shooterNumber":11,"time":41.06,"stageFinish":12,"hitFactor":3.4096,"countA":28,"countC":0,"countD":0,"countMiss":0,"countNoShoot":0,"countProcedural":0},{"stageNumber":3,"shooterNumber":12,"time":23.58,"stageFinish":10,"hitFactor":5.5131,"countA":23,"countC":5,"countD":0,"countMiss":0,"countNoShoot":0,"countProcedural":0},{"stageNumber":3,"shooterNumber":13,"time":13.4,"stageFinish":1,"hitFactor":9.3284,"countA":15,"countC":12,"countD":1,"countMiss":0,"countNoShoot":0,"countProcedural":0},{"stageNumber":3,"shooterNumber":14,"time":22.97,"stageFinish":8,"hitFactor":5.3983,"countA":16,"countC":10,"countD":2,"countMiss":0,"countNoShoot":0,"countProcedural":0},{"stageNumber":3,"shooterNumber":15,"time":16.58,"stageFinish":2,"hitFactor":8.082,"countA":22,"countC":6,"countD":0,"countMiss":0,"countNoShoot":0,"countProcedural":0},{"stageNumber":3,"shooterNumber":16,"time":17.0,"stageFinish":3,"hitFactor":7.8235,"countA":21,"countC":7,"countD":0,"countMiss":0,"countNoShoot":0,"countProcedural":0},{"stageNumber":3,"shooterNumber":17,"time":20.39,"stageFinish":4,"hitFactor":6.719,"countA":25,"countC":3,"countD":0,"countMiss":0,"countNoShoot":0,"countProcedural":0},{"stageNumber":3,"shooterNumber":18,"time":21.36,"stageFinish":6,"hitFactor":5.9925,"countA":23,"countC":4,"countD":1,"countMiss":0,"countNoShoot":0,"countProcedural":0},{"stageNumber":3,"shooterNumber":19,"time":19.7,"stageFinish":5,"hitFactor":6.7005,"countA":24,"countC":4,"countD":0,"countMiss":0,"countNoShoot":0,"countProcedural":0},{"stageNumber":3,"shooterNumber":20,"time":20.3,"stageFinish":7,"hitFactor":5.9113,"countA":18,"countC":10,"countD":0,"countMiss":0,"countNoShoot":0,"countProcedural":0},{"stageNumber":3,"shooterNumber":21,"time":32.77,"stageFinish":9,"hitFactor":3.906,"countA":26,"countC":2,"countD":0,"countMiss":0,"countNoShoot":0,"countProcedural":1},{"stageNumber":3,"shooterNumber":22,"time":63.51,"stageFinish":10,"hitFactor":1.921,"countA":19,"countC":9,"countD":0,"countMiss":0,"countNoShoot":0,"countProcedural":0},{"stageNumber":3,"shooterNumber":23,"time":10.91,"stageFinish":1,"hitFactor":12.2823,"countA":22,"countC":6,"countD":0,"countMiss":0,"countNoShoot":0,"countProcedural":0},{"stageNumber":3,"shooterNumber":24,"time":12.74,"stageFinish":2,"hitFactor":10.2826,"countA":23,"countC":3,"countD":2,"countMiss":0,"countNoShoot":0,"countProcedural":0},{"stageNumber":3,"shooterNumber":25,"time":14.02,"stageFinish":4,"hitFactor":8.1312,"countA":16,"countC":11,"countD":0,"countMiss":1,"countNoShoot":0,"countProcedural":0},{"stageNumber":3,"shooterNumber":26,"time":13.1,"stageFinish":3,"hitFactor":10.229,"countA":24,"countC":3,"countD":1,"countMiss":0,"countNoShoot":0,"countProcedural":0},{"stageNumber":3,"shooterNumber":27,"time":18.48,"stageFinish":5,"hitFactor":6.5476,"countA":23,"countC":4,"countD":0,"countMiss":1,"countNoShoot":0,"countProcedural":0},{"stageNumber":3,"shooterNumber":28,"time":24.73,"stageFinish":6,"hitFactor":5.4185,"countA":25,"countC":3,"countD":0,"countMiss":0,"countNoShoot":0,"countProcedural":0},{"stageNumber":3,"shooterNumber":29,"time":19.56,"stageFinish":7,"hitFactor":4.6524,"countA":9,"countC":15,"countD":3,"countMiss":1,"countNoShoot":1,"countProcedural":0},{"stageNumber":3,"shooterNumber":30,"time":24.96,"stageFinish":8,"hitFactor":4.1667,"countA":23,"countC":3,"countD":0,"countMiss":2,"countNoShoot":0,"countProcedural":0},{"stageNumber":3,"shooterNumber":31,"time":17.79,"stageFinish":9,"hitFactor":0.0,"countA":17,"countC":0,"countD":0,"countMiss":11,"countNoShoot":0,"countProcedural":5},{"stageNumber":3,"shooterNumber":32,"time":10.66,"stageFinish":1,"hitFactor":12.1951,"countA":23,"countC":5,"countD":0,"countMiss":0,"countNoShoot":0,"countProcedural":0},{"stageNumber":3,"shooterNumber":33,"time":11.52,"stageFinish":2,"hitFactor":9.7222,"countA":19,"countC":9,"countD":0,"countMiss":0,"countNoShoot":0,"countProcedural":1},{"stageNumber":3,"shooterNumber":34,"time":15.33,"stageFinish":3,"hitFactor":8.4801,"countA":23,"countC":5,"countD":0,"countMiss":0,"countNoShoot":0,"countProcedural":0},{"stageNumber":3,"shooterNumber":35,"time":16.35,"stageFinish":4,"hitFactor":7.5841,"countA":20,"countC":8,"countD":0,"countMiss":0,"countNoShoot":0,"countProcedural":0},{"stageNumber":3,"shooterNumber":36,"time":19.24,"stageFinish":5,"hitFactor":7.1726,"countA":27,"countC":1,"countD":0,"countMiss":0,"countNoShoot":0,"countProcedural":0},{"stageNumber":3,"shooterNumber":37,"time":15.25,"stageFinish":2,"hitFactor":5.9016,"countA":17,"countC":8,"countD":1,"countMiss":2,"countNoShoot":0,"countProcedural":0},{"stageNumber":3,"shooterNumber":38,"time":22.6,"stageFinish":1,"hitFactor":5.9292,"countA":25,"countC":3,"countD":0,"countMiss":0,"countNoShoot":0,"countProcedural":0},{"stageNumber":3,"shooterNumber":39,"time":33.34,"stageFinish":3,"hitFactor":4.1992,"countA":28,"countC":0,"countD":0,"countMiss":0,"countNoShoot":0,"countProcedural":0},{"stageNumber":3,"shooterNumber":40,"time":25.08,"stageFinish":1,"hitFactor":5.3828,"countA":25,"countC":2,"countD":1,"countMiss":0,"countNoShoot":0,"countProcedural":0},{"stageNumber":3,"shooterNumber":41,"time":26.05,"stageFinish":2,"hitFactor":5.2207,"countA":24,"countC":4,"countD":0,"countMiss":0,"countNoShoot":0,"countProcedural":0},{"stageNumber":3,"shooterNumber":42,"time":31.53,"stageFinish":3,"hitFactor":3.8059,"countA":19,"countC":8,"countD":1,"countMiss":0,"countNoShoot":0,"countProcedural":0},{"stageNumber":4,"shooterNumber":1,"time":14.17,"stageFinish":3,"hitFactor":3.2463,"countA":5,"countC":7,"countD":0,"countMiss":0,"countNoShoot":0,"countProcedural":0},{"stageNumber":4,"shooterNumber":2,"time":14.83,"stageFinish":6,"hitFactor":2.2252,"countA":10,"countC":1,"countD":0,"countMiss":1,"countNoShoot":1,"countProcedural":0},{"stageNumber":4,"shooterNumber":3,"time":18.43,"stageFinish":4,"hitFactor":3.0385,"countA":10,"countC":2,"countD":0,"countMiss":0,"countNoShoot":0,"countProcedural":0},{"stageNumber":4,"shooterNumber":4,"time":16.46,"stageFinish":2,"hitFactor":3.2807,"countA":9,"countC":3,"countD":0,"countMiss":0,"countNoShoot":0,"countProcedural":0},{"stageNumber":4,"shooterNumber":5,"time":19.2,"stageFinish":11,"hitFactor":1.0417,"countA":10,"countC":0,"countD":0,"countMiss":2,"countNoShoot":1,"countProcedural":0},{"stageNumber":4,"shooterNumber":6,"time":18.64,"stageFinish":5,"hitFactor":2.2532,"countA":8,"countC":4,"countD":0,"countMiss":0,"countNoShoot":1,"countProcedural":0},{"stageNumber":4,"shooterNumber":7,"time":17.46,"stageFinish":1,"hitFactor":3.4364,"countA":12,"countC":0,"countD":0,"countMiss":0,"countNoShoot":0,"countProcedural":0},{"stageNumber":4,"shooterNumber":8,"time":22.22,"stageFinish":9,"hitFactor":1.4851,"countA":10,"countC":1,"countD":0,"countMiss":1,"countNoShoot":1,"countProcedural":0},{"stageNumber":4,"shooterNumber":9,"time":22.84,"stageFinish":7,"hitFactor":1.9264,"countA":6,"countC":4,"countD":2,"countMiss":0,"countNoShoot":0,"countProcedural":0},{"stageNumber":4,"shooterNumber":10,"time":30.14,"stageFinish":10,"hitFactor":1.0949,"countA":10,"countC":1,"countD":0,"countMiss":1,"countNoShoot":1,"countProcedural":0},{"stageNumber":4,"shooterNumber":11,"time":36.04,"stageFinish":12,"hitFactor":0.9156,"countA":10,"countC":1,"countD":0,"countMiss":1,"countNoShoot":1,"countProcedural":0},{"stageNumber":4,"shooterNumber":12,"time":24.02,"stageFinish":8,"hitFactor":1.7485,"countA":8,"countC":4,"countD":0,"countMiss":0,"countNoShoot":0,"countProcedural":1},{"stageNumber":4,"shooterNumber":13,"time":14.01,"stageFinish":1,"hitFactor":3.4261,"countA":8,"countC":0,"countD":4,"countMiss":0,"countNoShoot":0,"countProcedural":0},{"stageNumber":4,"shooterNumber":14,"time":17.85,"stageFinish":2,"hitFactor":3.1933,"countA":9,"countC":3,"countD":0,"countMiss":0,"countNoShoot":0,"countProcedural":0},{"stageNumber":4,"shooterNumber":15,"time":20.07,"stageFinish":3,"hitFactor":2.6906,"countA":8,"countC":3,"countD":1,"countMiss":0,"countNoShoot":0,"countProcedural":0},{"stageNumber":4,"shooterNumber":16,"time":17.1,"stageFinish":4,"hitFactor":2.3977,"countA":7,"countC":4,"countD":0,"countMiss":1,"countNoShoot":0,"countProcedural":0},{"stageNumber":4,"shooterNumber":17,"time":22.38,"stageFinish":5,"hitFactor":2.3235,"countA":4,"countC":8,"countD":0,"countMiss":0,"countNoShoot":0,"countProcedural":0},{"stageNumber":4,"shooterNumber":18,"time":19.32,"stageFinish":7,"hitFactor":1.8116,"countA":7,"countC":3,"countD":1,"countMiss":1,"countNoShoot":0,"countProcedural":0},{"stageNumber":4,"shooterNumber":19,"time":26.99,"stageFinish":6,"hitFactor":1.9266,"countA":8,"countC":4,"countD":0,"countMiss":0,"countNoShoot":0,"countProcedural":0},{"stageNumber":4,"shooterNumber":20,"time":19.18,"stageFinish":10,"hitFactor":0.2086,"countA":4,"countC":4,"countD":2,"countMiss":2,"countNoShoot":1,"countProcedural":0},{"stageNumber":4,"shooterNumber":21,"time":31.08,"stageFinish":8,"hitFactor":1.3835,"countA":7,"countC":4,"countD":1,"countMiss":0,"countNoShoot":1,"countProcedural":0},{"stageNumber":4,"shooterNumber":22,"time":57.72,"stageFinish":9,"hitFactor":1.0049,"countA":11,"countC":1,"countD":0,"countMiss":0,"countNoShoot":0,"countProcedural":0},{"stageNumber":4,"shooterNumber":23,"time":14.4,"stageFinish":2,"hitFactor":4.0278,"countA":10,"countC":2,"countD":0,"countMiss":0,"countNoShoot":0,"countProcedural":0},{"stageNumber":4,"shooterNumber":24,"time":13.09,"stageFinish":1,"hitFactor":4.0489,"countA":7,"countC":4,"countD":1,"countMiss":0,"countNoShoot":0,"countProcedural":0},{"stageNumber":4,"shooterNumber":25,"time":18.57,"stageFinish":3,"hitFactor":3.1772,"countA":11,"countC":1,"countD":0,"countMiss":0,"countNoShoot":0,"countProcedural":0},{"stageNumber":4,"shooterNumber":26,"time":13.98,"stageFinish":4,"hitFactor":2.432,"countA":10,"countC":1,"countD":0,"countMiss":1,"countNoShoot":1,"countProcedural":0},{"stageNumber":4,"shooterNumber":27,"time":22.76,"stageFinish":9,"hitFactor":0.9666,"countA":8,"countC":3,"countD":0,"countMiss":1,"countNoShoot":2,"countProcedural":0},{"stageNumber":4,"shooterNumber":28,"time":27.33,"stageFinish":5,"hitFactor":2.1222,"countA":11,"countC":1,"countD":0,"countMiss":0,"countNoShoot":0,"countProcedural":0},{"stageNumber":4,"shooterNumber":29,"time":24.86,"stageFinish":6,"hitFactor":1.9308,"countA":6,"countC":3,"countD":3,"countMiss":0,"countNoShoot":0,"countProcedural":0},{"stageNumber":4,"shooterNumber":30,"time":29.78,"stageFinish":7,"hitFactor":1.8133,"countA":9,"countC":3,"countD":0,"countMiss":0,"countNoShoot":0,"countProcedural":0},{"stageNumber":4,"shooterNumber":31,"time":26.67,"stageFinish":8,"hitFactor":1.7998,"countA":6,"countC":6,"countD":0,"countMiss":0,"countNoShoot":0,"countProcedural":0},{"stageNumber":4,"shooterNumber":32,"time":11.93,"stageFinish":4,"hitFactor":2.7661,"countA":10,"countC":1,"countD":0,"countMiss":1,"countNoShoot":1,"countProcedural":0},{"stageNumber":4,"shooterNumber":33,"time":17.83,"stageFinish":3,"hitFactor":2.9164,"countA":8,"countC":4,"countD":0,"countMiss":0,"countNoShoot":0,"countProcedural":0},{"stageNumber":4,"shooterNumber":34,"time":15.97,"stageFinish":1,"hitFactor":3.6318,"countA":11,"countC":1,"countD":0,"countMiss":0,"countNoShoot":0,"countProcedural":0},{"stageNumber":4,"shooterNumber":35,"time":18.76,"stageFinish":2,"hitFactor":2.9851,"countA":10,"countC":2,"countD":0,"countMiss":0,"countNoShoot":0,"countProcedural":0},{"stageNumber":4,"shooterNumber":36,"time":21.6,"stageFinish":5,"hitFactor":2.3148,"countA":12,"countC":0,"countD":0,"countMiss":0,"countNoShoot":1,"countProcedural":0},{"stageNumber":4,"shooterNumber":37,"time":14.35,"stageFinish":1,"hitFactor":3.6237,"countA":8,"countC":4,"countD":0,"countMiss":0,"countNoShoot":0,"countProcedural":0},{"stageNumber":4,"shooterNumber":38,"time":21.91,"stageFinish":2,"hitFactor":2.6472,"countA":11,"countC":1,"countD":0,"countMiss":0,"countNoShoot":0,"countProcedural":0},{"stageNumber":4,"shooterNumber":39,"time":27.42,"stageFinish":3,"hitFactor":0.2918,"countA":9,"countC":1,"countD":0,"countMiss":2,"countNoShoot":2,"countProcedural":0},{"stageNumber":4,"shooterNumber":40,"time":14.65,"stageFinish":1,"hitFactor":3.959,"countA":10,"countC":2,"countD":0,"countMiss":0,"countNoShoot":0,"countProcedural":0},{"stageNumber":4,"shooterNumber":41,"time":21.96,"stageFinish":2,"hitFactor":1.5027,"countA":9,"countC":2,"countD":0,"countMiss":1,"countNoShoot":1,"countProcedural":0},{"stageNumber":4,"shooterNumber":42,"time":33.74,"stageFinish":3,"hitFactor":0.0296,"countA":2,"countC":6,"countD":3,"countMiss":1,"countNoShoot":2,"countProcedural":0},{"stageNumber":5,"shooterNumber":1,"time":12.05,"stageFinish":1,"hitFactor":7.8008,"countA":14,"countC":8,"countD":0,"countMiss":0,"countNoShoot":0,"countProcedural":0},{"stageNumber":5,"shooterNumber":2,"time":13.12,"stageFinish":3,"hitFactor":6.3262,"countA":15,"countC":6,"countD":0,"countMiss":1,"countNoShoot":0,"countProcedural":0},{"stageNumber":5,"shooterNumber":3,"time":15.98,"stageFinish":2,"hitFactor":6.6333,"countA":20,"countC":2,"countD":0,"countMiss":0,"countNoShoot":0,"countProcedural":0},{"stageNumber":5,"shooterNumber":4,"time":17.04,"stageFinish":5,"hitFactor":5.9859,"countA":19,"countC":2,"countD":1,"countMiss":0,"countNoShoot":0,"countProcedural":0},{"stageNumber":5,"shooterNumber":5,"time":18.43,"stageFinish":6,"hitFactor":5.5345,"countA":18,"countC":4,"countD":0,"countMiss":0,"countNoShoot":0,"countProcedural":0},{"stageNumber":5,"shooterNumber":6,"time":17.69,"stageFinish":4,"hitFactor":6.1051,"countA":21,"countC":1,"countD":0,"countMiss":0,"countNoShoot":0,"countProcedural":0},{"stageNumber":5,"shooterNumber":7,"time":16.12,"stageFinish":7,"hitFactor":5.4591,"countA":11,"countC":11,"countD":0,"countMiss":0,"countNoShoot":0,"countProcedural":0},{"stageNumber":5,"shooterNumber":8,"time":23.03,"stageFinish":8,"hitFactor":4.5158,"countA":19,"countC":3,"countD":0,"countMiss":0,"countNoShoot":0,"countProcedural":0},{"stageNumber":5,"shooterNumber":9,"time":21.17,"stageFinish":9,"hitFactor":3.9206,"countA":17,"countC":2,"countD":2,"countMiss":1,"countNoShoot":0,"countProcedural":0},{"stageNumber":5,"shooterNumber":10,"time":43.03,"stageFinish":11,"hitFactor":2.2775,"countA":16,"countC":6,"countD":0,"countMiss":0,"countNoShoot":0,"countProcedural":0},{"stageNumber":5,"shooterNumber":11,"time":35.53,"stageFinish":10,"hitFactor":2.9271,"countA":19,"countC":3,"countD":0,"countMiss":0,"countNoShoot":0,"countProcedural":0},{"stageNumber":5,"shooterNumber":12,"time":26.58,"stageFinish":12,"hitFactor":1.9564,"countA":9,"countC":8,"countD":3,"countMiss":2,"countNoShoot":0,"countProcedural":0},{"stageNumber":5,"shooterNumber":13,"time":13.5,"stageFinish":1,"hitFactor":7.4074,"countA":14,"countC":7,"countD":1,"countMiss":0,"countNoShoot":0,"countProcedural":0},{"stageNumber":5,"shooterNumber":14,"time":22.91,"stageFinish":6,"hitFactor":4.0157,"countA":12,"countC":6,"countD":4,"countMiss":0,"countNoShoot":0,"countProcedural":0},{"stageNumber":5,"shooterNumber":15,"time":21.6,"stageFinish":4,"hitFactor":4.537,"countA":14,"countC":6,"countD":2,"countMiss":0,"countNoShoot":0,"countProcedural":0},{"stageNumber":5,"shooterNumber":16,"time":24.83,"stageFinish":5,"hitFactor":4.269,"countA":18,"countC":4,"countD":0,"countMiss":0,"countNoShoot":0,"countProcedural":0},{"stageNumber":5,"shooterNumber":17,"time":22.33,"stageFinish":2,"hitFactor":4.7918,"countA":19,"countC":3,"countD":0,"countMiss":0,"countNoShoot":0,"countProcedural":0},{"stageNumber":5,"shooterNumber":18,"time":18.3,"stageFinish":3,"hitFactor":4.6995,"countA":12,"countC":8,"countD":2,"countMiss":0,"countNoShoot":0,"countProcedural":0},{"stageNumber":5,"shooterNumber":19,"time":42.41,"stageFinish":10,"hitFactor":2.5466,"countA":21,"countC":1,"countD":0,"countMiss":0,"countNoShoot":0,"countProcedural":0},{"stageNumber":5,"shooterNumber":20,"time":25.44,"stageFinish":8,"hitFactor":2.9088,"countA":15,"countC":6,"countD":1,"countMiss":0,"countNoShoot":2,"countProcedural":0},{"stageNumber":5,"shooterNumber":21,"time":31.95,"stageFinish":7,"hitFactor":3.0673,"countA":14,"countC":6,"countD":2,"countMiss":0,"countNoShoot":0,"countProcedural":0},{"stageNumber":5,"shooterNumber":22,"time":37.71,"stageFinish":9,"hitFactor":2.864,"countA":21,"countC":1,"countD":0,"countMiss":0,"countNoShoot":0,"countProcedural":0},{"stageNumber":5,"shooterNumber":23,"time":11.51,"stageFinish":1,"hitFactor":8.4275,"countA":13,"countC":7,"countD":2,"countMiss":0,"countNoShoot":0,"countProcedural":0},{"stageNumber":5,"shooterNumber":24,"time":11.06,"stageFinish":3,"hitFactor":6.6004,"countA":13,"countC":6,"countD":2,"countMiss":1,"countNoShoot":1,"countProcedural":0},{"stageNumber":5,"shooterNumber":25,"time":15.02,"stageFinish":2,"hitFactor":6.9907,"countA":17,"countC":5,"countD":0,"countMiss":0,"countNoShoot":0,"countProcedural":0},{"stageNumber":5,"shooterNumber":26,"time":13.99,"stageFinish":4,"hitFactor":6.5046,"countA":13,"countC":9,"countD":0,"countMiss":0,"countNoShoot":1,"countProcedural":0},{"stageNumber":5,"shooterNumber":27,"time":21.91,"stageFinish":5,"hitFactor":4.7923,"countA":17,"countC":5,"countD":0,"countMiss":0,"countNoShoot":0,"countProcedural":0},{"stageNumber":5,"shooterNumber":28,"time":29.37,"stageFinish":8,"hitFactor":3.6091,"countA":20,"countC":2,"countD":0,"countMiss":0,"countNoShoot":0,"countProcedural":0},{"stageNumber":5,"shooterNumber":29,"time":21.23,"stageFinish":7,"hitFactor":4.4748,"countA":13,"countC":6,"countD":3,"countMiss":0,"countNoShoot":0,"countProcedural":0},{"stageNumber":5,"shooterNumber":30,"time":24.31,"stageFinish":9,"hitFactor":3.332,"countA":14,"countC":7,"countD":0,"countMiss":1,"countNoShoot":0,"countProcedural":0},{"stageNumber":5,"shooterNumber":31,"time":23.41,"stageFinish":6,"hitFactor":4.6134,"countA":21,"countC":1,"countD":0,"countMiss":0,"countNoShoot":0,"countProcedural":0},{"stageNumber":5,"shooterNumber":32,"time":10.99,"stageFinish":2,"hitFactor":8.9172,"countA":16,"countC":6,"countD":0,"countMiss":0,"countNoShoot":0,"countProcedural":0},{"stageNumber":5,"shooterNumber":33,"time":10.54,"stageFinish":1,"hitFactor":9.6774,"countA":20,"countC":0,"countD":2,"countMiss":0,"countNoShoot":0,"countProcedural":0},{"stageNumber":5,"shooterNumber":34,"time":13.74,"stageFinish":3,"hitFactor":7.1325,"countA":16,"countC":6,"countD":0,"countMiss":0,"countNoShoot":0,"countProcedural":0},{"stageNumber":5,"shooterNumber":35,"time":14.79,"stageFinish":4,"hitFactor":6.7613,"countA":17,"countC":5,"countD":0,"countMiss":0,"countNoShoot":0,"countProcedural":0},{"stageNumber":5,"shooterNumber":36,"time":20.1,"stageFinish":5,"hitFactor":5.4726,"countA":22,"countC":0,"countD":0,"countMiss":0,"countNoShoot":0,"countProcedural":0},{"stageNumber":5,"shooterNumber":37,"time":15.28,"stageFinish":1,"hitFactor":5.3665,"countA":13,"countC":9,"countD":0,"countMiss":0,"countNoShoot":1,"countProcedural":0},{"stageNumber":5,"shooterNumber":38,"time":20.19,"stageFinish":2,"hitFactor":4.5567,"countA":15,"countC":5,"countD":2,"countMiss":0,"countNoShoot":0,"countProcedural":0},{"stageNumber":5,"shooterNumber":39,"time":34.04,"stageFinish":3,"hitFactor":3.1727,"countA":21,"countC":1,"countD":0,"countMiss":0,"countNoShoot":0,"countProcedural":0},{"stageNumber":5,"shooterNumber":40,"time":17.36,"stageFinish":1,"hitFactor":5.818,"countA":15,"countC":6,"countD":1,"countMiss":0,"countNoShoot":0,"countProcedural":0},{"stageNumber":5,"shooterNumber":41,"time":26.12,"stageFinish":2,"hitFactor":3.7902,"countA":21,"countC":1,"countD":0,"countMiss":0,"countNoShoot":1,"countProcedural":0},{"stageNumber":5,"shooterNumber":42,"time":40.91,"stageFinish":3,"hitFactor":1.3444,"countA":9,"countC":9,"countD":3,"countMiss":1,"countNoShoot":1,"countProcedural":0},{"stageNumber":6,"shooterNumber":1,"time":28.2,"stageFinish":4,"hitFactor":4.3262,"countA":16,"countC":14,"countD":0,"countMiss":0,"countNoShoot":0,"countProcedural":0},{"stageNumber":6,"shooterNumber":2,"time":24.74,"stageFinish":3,"hitFactor":4.81,"countA":22,"countC":6,"countD":1,"countMiss":1,"countNoShoot":0,"countProcedural":0},{"stageNumber":6,"shooterNumber":3,"time":29.03,"stageFinish":2,"hitFactor":5.0293,"countA":28,"countC":2,"countD":0,"countMiss":0,"countNoShoot":0,"countProcedural":0},{"stageNumber":6,"shooterNumber":4,"time":36.99,"stageFinish":8,"hitFactor":4.0011,"countA":29,"countC":1,"countD":0,"countMiss":0,"countNoShoot":0,"countProcedural":0},{"stageNumber":6,"shooterNumber":5,"time":28.6,"stageFinish":1,"hitFactor":5.035,"countA":27,"countC":3,"countD":0,"countMiss":0,"countNoShoot":0,"countProcedural":0},{"stageNumber":6,"shooterNumber":6,"time":32.35,"stageFinish":6,"hitFactor":4.204,"countA":23,"countC":7,"countD":0,"countMiss":0,"countNoShoot":0,"countProcedural":0},{"stageNumber":6,"shooterNumber":7,"time":31.31,"stageFinish":5,"hitFactor":4.2798,"countA":23,"countC":6,"countD":1,"countMiss":0,"countNoShoot":0,"countProcedural":0},{"stageNumber":6,"shooterNumber":8,"time":37.17,"stageFinish":7,"hitFactor":4.0355,"countA":30,"countC":0,"countD":0,"countMiss":0,"countNoShoot":0,"countProcedural":0},{"stageNumber":6,"shooterNumber":9,"time":47.93,"stageFinish":9,"hitFactor":2.8375,"countA":24,"countC":5,"countD":1,"countMiss":0,"countNoShoot":0,"countProcedural":0},{"stageNumber":6,"shooterNumber":10,"time":54.78,"stageFinish":10,"hitFactor":2.5922,"countA":26,"countC":4,"countD":0,"countMiss":0,"countNoShoot":0,"countProcedural":0},{"stageNumber":6,"shooterNumber":11,"time":60.53,"stageFinish":11,"hitFactor":1.966,"countA":26,"countC":3,"countD":0,"countMiss":1,"countNoShoot":1,"countProcedural":0},{"stageNumber":6,"shooterNumber":12,"time":50.3,"stageFinish":12,"hitFactor":0.3579,"countA":11,"countC":10,"countD":3,"countMiss":6,"countNoShoot":1,"countProcedural":0},{"stageNumber":6,"shooterNumber":13,"time":27.91,"stageFinish":1,"hitFactor":5.1594,"countA":24,"countC":6,"countD":0,"countMiss":0,"countNoShoot":0,"countProcedural":0},{"stageNumber":6,"shooterNumber":14,"time":26.84,"stageFinish":2,"hitFactor":5.0298,"countA":19,"countC":9,"countD":2,"countMiss":0,"countNoShoot":0,"countProcedural":0},{"stageNumber":6,"shooterNumber":15,"time":34.52,"stageFinish":3,"hitFactor":3.9977,"countA":20,"countC":9,"countD":1,"countMiss":0,"countNoShoot":0,"countProcedural":0},{"stageNumber":6,"shooterNumber":16,"time":35.64,"stageFinish":4,"hitFactor":3.844,"countA":19,"countC":10,"countD":1,"countMiss":0,"countNoShoot":0,"countProcedural":0},{"stageNumber":6,"shooterNumber":17,"time":44.16,"stageFinish":5,"hitFactor":3.1024,"countA":19,"countC":10,"countD":1,"countMiss":0,"countNoShoot":0,"countProcedural":0},{"stageNumber":6,"shooterNumber":18,"time":42.05,"stageFinish":6,"hitFactor":2.2592,"countA":20,"countC":8,"countD":1,"countMiss":1,"countNoShoot":2,"countProcedural":0},{"stageNumber":6,"shooterNumber":19,"time":57.67,"stageFinish":7,"hitFactor":2.2369,"countA":26,"countC":3,"countD":0,"countMiss":1,"countNoShoot":0,"countProcedural":0},{"stageNumber":6,"shooterNumber":20,"time":52.73,"stageFinish":9,"hitFactor":1.5172,"countA":19,"countC":8,"countD":1,"countMiss":2,"countNoShoot":2,"countProcedural":0},{"stageNumber":6,"shooterNumber":21,"time":88.91,"stageFinish":10,"hitFactor":1.1697,"countA":16,"countC":9,"countD":4,"countMiss":1,"countNoShoot":1,"countProcedural":0},{"stageNumber":6,"shooterNumber":22,"time":75.85,"stageFinish":8,"hitFactor":1.8194,"countA":24,"countC":6,"countD":0,"countMiss":0,"countNoShoot":0,"countProcedural":0},{"stageNumber":6,"shooterNumber":23,"time":20.16,"stageFinish":4,"hitFactor":4.0675,"countA":22,"countC":8,"countD":0,"countMiss":0,"countNoShoot":0,"countProcedural":6},{"stageNumber":6,"shooterNumber":24,"time":20.02,"stageFinish":1,"hitFactor":6.6933,"countA":18,"countC":10,"countD":2,"countMiss":0,"countNoShoot":0,"countProcedural":0},{"stageNumber":6,"shooterNumber":25,"time":22.5,"stageFinish":2,"hitFactor":6.0,"countA":19,"countC":9,"countD":2,"countMiss":0,"countNoShoot":0,"countProcedural":0},{"stageNumber":6,"shooterNumber":26,"time":24.3,"stageFinish":3,"hitFactor":4.6914,"countA":18,"countC":11,"countD":0,"countMiss":1,"countNoShoot":1,"countProcedural":0},{"stageNumber":6,"shooterNumber":27,"time":43.16,"stageFinish":5,"hitFactor":3.1279,"countA":21,"countC":6,"countD":3,"countMiss":0,"countNoShoot":0,"countProcedural":0},{"stageNumber":6,"shooterNumber":28,"time":45.48,"stageFinish":7,"hitFactor":2.9024,"countA":26,"countC":4,"countD":0,"countMiss":0,"countNoShoot":1,"countProcedural":0},{"stageNumber":6,"shooterNumber":29,"time":36.9,"stageFinish":6,"hitFactor":2.981,"countA":14,"countC":10,"countD":5,"countMiss":1,"countNoShoot":0,"countProcedural":0},{"stageNumber":6,"shooterNumber":30,"time":49.35,"stageFinish":8,"hitFactor":2.5329,"countA":24,"countC":5,"countD":0,"countMiss":1,"countNoShoot":0,"countProcedural":0},{"stageNumber":6,"shooterNumber":31,"time":76.02,"stageFinish":9,"hitFactor":1.4996,"countA":22,"countC":8,"countD":0,"countMiss":0,"countNoShoot":0,"countProcedural":2},{"stageNumber":6,"shooterNumber":32,"time":17.8,"stageFinish":3,"hitFactor":5.7865,"countA":21,"countC":5,"countD":3,"countMiss":1,"countNoShoot":1,"countProcedural":0},{"stageNumber":6,"shooterNumber":33,"time":18.53,"stageFinish":1,"hitFactor":6.7998,"countA":19,"countC":10,"countD":1,"countMiss":0,"countNoShoot":0,"countProcedural":0},{"stageNumber":6,"shooterNumber":34,"time":22.63,"stageFinish":2,"hitFactor":6.2749,"countA":27,"countC":2,"countD":1,"countMiss":0,"countNoShoot":0,"countProcedural":0},{"stageNumber":6,"shooterNumber":35,"time":27.12,"stageFinish":5,"hitFactor":4.1667,"countA":19,"countC":9,"countD":1,"countMiss":1,"countNoShoot":0,"countProcedural":0},{"stageNumber":6,"shooterNumber":36,"time":25.82,"stageFinish":4,"hitFactor":5.6545,"countA":28,"countC":2,"countD":0,"countMiss":0,"countNoShoot":0,"countProcedural":0},{"stageNumber":6,"shooterNumber":37,"time":33.07,"stageFinish":2,"hitFactor":2.7215,"countA":18,"countC":10,"countD":0,"countMiss":2,"countNoShoot":1,"countProcedural":0},{"stageNumber":6,"shooterNumber":38,"time":35.67,"stageFinish":1,"hitFactor":3.8688,"countA":24,"countC":6,"countD":0,"countMiss":0,"countNoShoot":0,"countProcedural":0},{"stageNumber":6,"shooterNumber":39,"time":43.99,"stageFinish":3,"hitFactor":2.2732,"countA":23,"countC":5,"countD":0,"countMiss":2,"countNoShoot":1,"countProcedural":0},{"stageNumber":6,"shooterNumber":40,"time":33.24,"stageFinish":1,"hitFactor":3.7906,"countA":22,"countC":6,"countD":1,"countMiss":1,"countNoShoot":0,"countProcedural":0},{"stageNumber":6,"shooterNumber":41,"time":54.45,"stageFinish":2,"hitFactor":2.3508,"countA":20,"countC":9,"countD":1,"countMiss":0,"countNoShoot":1,"countProcedural":0},{"stageNumber":6,"shooterNumber":42,"time":83.96,"stageFinish":3,"hitFactor":1.1077,"countA":16,"countC":10,"countD":3,"countMiss":1,"countNoShoot":1,"countProcedural":0}]}